{"universal_minecraft:grass_block": "1", "universal_minecraft:water": "2", "universal_minecraft:andesite": "3", "universal_minecraft:snow": "4", "universal_minecraft:cobblestone": "5", "universal_minecraft:stone": "6", "universal_minecraft:plant": "7", "universal_minecraft:leaves": "8", "universal_minecraft:snow_block": "9", "universal_minecraft:stone_bricks": "a", "universal_minecraft:double_plant": "b", "universal_minecraft:wood": "c", "universal_minecraft:ice": "d", "universal_minecraft:slab": "e", "universal_minecraft:coarse_dirt": "f", "universal_minecraft:seagrass": "g", "universal_minecraft:grass_path": "h", "universal_minecraft:wall": "i", "universal_minecraft:moss_block": "j", "universal_minecraft:planks": "k", "universal_minecraft:fence": "l", "universal_minecraft:tall_seagrass": "m", "universal_minecraft:deepslate_tiles": "n", "universal_minecraft:trapdoor": "o", "universal_minecraft:dirt": "p", "universal_minecraft:moss_carpet": "q", "universal_minecraft:concrete": "r", "universal_minecraft:sapling": "s", "universal_minecraft:wall_sign": "t", "universal_minecraft:vine": "u", "universal_minecraft:packed_mud": "v", "universal_minecraft:kelp": "w", "universal_minecraft:stained_glass_pane": "x", "universal_minecraft:mossy_cobblestone": "y", "universal_minecraft:cracked_deepslate_tiles": "z", "universal_minecraft:cobbled_deepslate": "A", "universal_minecraft:brown_mushroom_block": "B", "universal_minecraft:terracotta": "C", "universal_minecraft:barrel": "D", "universal_minecraft:smooth_stone": "E", "universal_minecraft:stained_glass": "F", "universal_minecraft:muddy_mangrove_roots": "G", "universal_minecraft:stained_terracotta": "H", "universal_minecraft:wool": "I", "universal_minecraft:glazed_terracotta": "J", "universal_minecraft:mud": "K", "universal_minecraft:log": "L", "universal_minecraft:coral": "M", "universal_minecraft:deepslate_bricks": "N", "universal_minecraft:polished_deepslate": "O", "universal_minecraft:waxed_oxidized_copper": "P", "universal_minecraft:glass_pane": "Q", "universal_minecraft:button": "R", "universal_minecraft:chiseled_polished_blackstone": "S", "universal_minecraft:glow_lichen": "T", "universal_minecraft:lightning_rod": "U", "universal_minecraft:iron_bars": "V", "universal_minecraft:tnt": "W", "universal_minecraft:campfire": "X", "universal_minecraft:wall_banner": "Y", "universal_minecraft:fence_gate": "Z"}